odoo/addons/product_multi_price/README.rst
odoo/addons/product_multi_price/__init__.py
odoo/addons/product_multi_price/__manifest__.py
odoo/addons/product_multi_price/demo/multi_price_demo_data.xml
odoo/addons/product_multi_price/i18n/es.po
odoo/addons/product_multi_price/i18n/product_multi_price.pot
odoo/addons/product_multi_price/models/__init__.py
odoo/addons/product_multi_price/models/product_multi_price.py
odoo/addons/product_multi_price/models/product_pricelist.py
odoo/addons/product_multi_price/models/product_product.py
odoo/addons/product_multi_price/models/product_template.py
odoo/addons/product_multi_price/readme/CONFIGURE.rst
odoo/addons/product_multi_price/readme/CONTRIBUTORS.rst
odoo/addons/product_multi_price/readme/DESCRIPTION.rst
odoo/addons/product_multi_price/readme/ROADMAP.rst
odoo/addons/product_multi_price/readme/USAGE.rst
odoo/addons/product_multi_price/security/ir.model.access.csv
odoo/addons/product_multi_price/security/multi_price_security.xml
odoo/addons/product_multi_price/static/description/icon.png
odoo/addons/product_multi_price/static/description/index.html
odoo/addons/product_multi_price/tests/__init__.py
odoo/addons/product_multi_price/tests/test_product_multi_price.py
odoo/addons/product_multi_price/views/multi_price_views.xml
odoo/addons/product_multi_price/views/product_pricelist_views.xml
odoo/addons/product_multi_price/views/product_views.xml
odoo11_addon_product_multi_price-11.0.1.2.0.dist-info/METADATA
odoo11_addon_product_multi_price-11.0.1.2.0.dist-info/WHEEL
odoo11_addon_product_multi_price-11.0.1.2.0.dist-info/top_level.txt
odoo11_addon_product_multi_price-11.0.1.2.0.dist-info/RECORD
